LICENSE.rst
README.rst
pyproject.toml
setup.cfg
setup.py
./dysmalpy/models/cutils.c
dysmalpy/__init__.py
dysmalpy/aperture_classes.py
dysmalpy/check_build.py
dysmalpy/config.py
dysmalpy/data_classes.py
dysmalpy/data_io.py
dysmalpy/galaxy.py
dysmalpy/instrument.py
dysmalpy/lensing.py
dysmalpy/observation.py
dysmalpy/parameters.py
dysmalpy/plotting.py
dysmalpy/pyqt_dysmalpy_gui.py
dysmalpy/utils.py
dysmalpy/utils_io.py
dysmalpy/utils_least_chi_squares_1d_fitter.py
dysmalpy.egg-info/PKG-INFO
dysmalpy.egg-info/SOURCES.txt
dysmalpy.egg-info/dependency_links.txt
dysmalpy.egg-info/requires.txt
dysmalpy.egg-info/top_level.txt
dysmalpy/../LICENSE.rst
dysmalpy/data/deprojected_sersic_models_tables/deproj_sersic_model_n0.5_invq0.50.fits
dysmalpy/data/deprojected_sersic_models_tables/deproj_sersic_model_n0.5_invq0.67.fits
dysmalpy/data/deprojected_sersic_models_tables/deproj_sersic_model_n0.5_invq1.00.fits
dysmalpy/data/deprojected_sersic_models_tables/deproj_sersic_model_n0.5_invq1.11.fits
dysmalpy/data/deprojected_sersic_models_tables/deproj_sersic_model_n0.5_invq1.25.fits
dysmalpy/data/deprojected_sersic_models_tables/deproj_sersic_model_n0.5_invq1.43.fits
dysmalpy/data/deprojected_sersic_models_tables/deproj_sersic_model_n0.5_invq1.67.fits
dysmalpy/data/deprojected_sersic_models_tables/deproj_sersic_model_n0.5_invq10.00.fits
dysmalpy/data/deprojected_sersic_models_tables/deproj_sersic_model_n0.5_invq100.00.fits
dysmalpy/data/deprojected_sersic_models_tables/deproj_sersic_model_n0.5_invq2.00.fits
dysmalpy/data/deprojected_sersic_models_tables/deproj_sersic_model_n0.5_invq2.50.fits
dysmalpy/data/deprojected_sersic_models_tables/deproj_sersic_model_n0.5_invq20.00.fits
dysmalpy/data/deprojected_sersic_models_tables/deproj_sersic_model_n0.5_invq3.00.fits
dysmalpy/data/deprojected_sersic_models_tables/deproj_sersic_model_n0.5_invq3.33.fits
dysmalpy/data/deprojected_sersic_models_tables/deproj_sersic_model_n0.5_invq4.00.fits
dysmalpy/data/deprojected_sersic_models_tables/deproj_sersic_model_n0.5_invq5.00.fits
dysmalpy/data/deprojected_sersic_models_tables/deproj_sersic_model_n0.5_invq6.00.fits
