Metadata-Version: 2.1
Name: dysmalpy
Version: 2.0.0
Summary: A modelling and fitting package for galaxy kinematics.
Home-page: https://github.com/dysmalpy/dysmalpy
Author: MPE IR/Sub-mm Group
Author-email: dysmalpy@mpe.mpg.de
Project-URL: Bug Tracker, https://github.com/dysmalpy/dysmalpy/issues
Project-URL: Source Code, https://github.com/dysmalpy/dysmalpy
Classifier: Development Status :: 5 - Production/Stable
Classifier: Environment :: Console
Classifier: Intended Audience :: Science/Research
Classifier: Topic :: Scientific/Engineering :: Physics
Classifier: Programming Language :: Python :: 3.10
Classifier: Programming Language :: Python :: 3.11
Classifier: Natural Language :: English
License-File: LICENSE.rst
Requires-Dist: numpy>=1.24.3
Requires-Dist: scipy>=1.9.3
Requires-Dist: matplotlib
Requires-Dist: astropy>=5.3
Requires-Dist: emcee>=3
Requires-Dist: corner>=2.2.2
Requires-Dist: cython
Requires-Dist: dill>=0.3.7
Requires-Dist: shapely>=2
Requires-Dist: photutils>=1.8.0
Requires-Dist: spectral-cube>=0.6.0
Requires-Dist: radio-beam>=0.3.3
Requires-Dist: h5py>=3.8.0
Requires-Dist: pandas
Requires-Dist: six
Requires-Dist: ipython
Requires-Dist: defaults
Requires-Dist: dynesty>=2.1.3
Requires-Dist: pytest
Requires-Dist: multiprocess
